colorsails/__init__.py
colorsails/helpers.py
colorsails/sails.py
colorsails-0.1.0.dist-info/METADATA
colorsails-0.1.0.dist-info/WHEEL
colorsails-0.1.0.dist-info/top_level.txt
colorsails-0.1.0.dist-info/RECORD
